elasticsearch1_dsl/__init__.py
elasticsearch1_dsl/aggs.py
elasticsearch1_dsl/analysis.py
elasticsearch1_dsl/connections.py
elasticsearch1_dsl/document.py
elasticsearch1_dsl/exceptions.py
elasticsearch1_dsl/faceted_search.py
elasticsearch1_dsl/field.py
elasticsearch1_dsl/filter.py
elasticsearch1_dsl/function.py
elasticsearch1_dsl/index.py
elasticsearch1_dsl/mapping.py
elasticsearch1_dsl/query.py
elasticsearch1_dsl/result.py
elasticsearch1_dsl/search.py
elasticsearch1_dsl/serializer.py
elasticsearch1_dsl/utils.py
elasticsearch1_dsl-0.0.12.dist-info/DESCRIPTION.rst
elasticsearch1_dsl-0.0.12.dist-info/METADATA
elasticsearch1_dsl-0.0.12.dist-info/RECORD
elasticsearch1_dsl-0.0.12.dist-info/WHEEL
elasticsearch1_dsl-0.0.12.dist-info/metadata.json
elasticsearch1_dsl-0.0.12.dist-info/top_level.txt
